setup.py
pytest_start_from/__init__.py
pytest_start_from.egg-info/PKG-INFO
pytest_start_from.egg-info/SOURCES.txt
pytest_start_from.egg-info/dependency_links.txt
pytest_start_from.egg-info/entry_points.txt
pytest_start_from.egg-info/requires.txt
pytest_start_from.egg-info/top_level.txt