Metadata-Version: 1.0
Name: pytest-start-from
Version: 0.1.0
Summary: Start pytest run from a given point
Home-page: https://bitbucket.org/dtao/pytest-start-from
Author: Dan Tao
Author-email: daniel.tao@gmail.com
License: UNKNOWN
Platform: UNKNOWN
